LICENSE
MANIFEST.in
README.rst
setup.py
src/pandas_datareader_gdax/__init__.py
src/pandas_datareader_gdax.egg-info/PKG-INFO
src/pandas_datareader_gdax.egg-info/SOURCES.txt
src/pandas_datareader_gdax.egg-info/dependency_links.txt
src/pandas_datareader_gdax.egg-info/requires.txt
src/pandas_datareader_gdax.egg-info/top_level.txt