Metadata-Version: 1.1
Name: pandas-datareader-gdax
Version: 0.1.1
Summary: GDAX data for Pandas in the style of DataReader.
Home-page: https://github.com/bfolkens/pandas-datareader-gdax
Author: Brad Folkens
Author-email: bfolkens@gmail.com
License: BSD license
Keywords: python,finance,quant,data,crypto,bitcoin,gdax
Platform: UNKNOWN
Classifier: Development Status :: 3 - Alpha
Classifier: Intended Audience :: Developers
Classifier: License :: OSI Approved :: BSD License
Classifier: Operating System :: Unix
Classifier: Operating System :: POSIX
Classifier: Operating System :: Microsoft :: Windows
Classifier: Programming Language :: Python
Classifier: Programming Language :: Python :: 2.7
Classifier: Programming Language :: Python :: 3
Classifier: Programming Language :: Python :: 3.3
Classifier: Programming Language :: Python :: 3.4
Classifier: Programming Language :: Python :: 3.5
Classifier: Programming Language :: Python :: 3.6
Classifier: Programming Language :: Python :: Implementation :: CPython
Classifier: Programming Language :: Python :: Implementation :: PyPy
Classifier: Topic :: Software Development :: Libraries
